pydantic_regex/__init__.py
pydantic_regex/errors.py
pydantic_regex/regex.py
pydantic_regex-1.0.0.dist-info/WHEEL
pydantic_regex-1.0.0.dist-info/METADATA
pydantic_regex-1.0.0.dist-info/RECORD
